C11JiaochengCYuyanBianchengWangFix1/README.md
C11JiaochengCYuyanBianchengWangFix1/__init__.py
C11JiaochengCYuyanBianchengWangFix1/__main__.py
C11JiaochengCYuyanBianchengWangFix1/file.epub
C11JiaochengCYuyanBianchengWangFix1/index.html
C11JiaochengCYuyanBianchengWangFix1/css/__init__.py
C11JiaochengCYuyanBianchengWangFix1/css/annotations.css
C11JiaochengCYuyanBianchengWangFix1/css/main.css
C11JiaochengCYuyanBianchengWangFix1/css/normalize.css
C11JiaochengCYuyanBianchengWangFix1/css/popup.css
C11JiaochengCYuyanBianchengWangFix1/font/__init__.py
C11JiaochengCYuyanBianchengWangFix1/font/fontello.eot
C11JiaochengCYuyanBianchengWangFix1/font/fontello.svg
C11JiaochengCYuyanBianchengWangFix1/font/fontello.ttf
C11JiaochengCYuyanBianchengWangFix1/font/fontello.woff
C11JiaochengCYuyanBianchengWangFix1/img/__init__.py
C11JiaochengCYuyanBianchengWangFix1/img/annotator-glyph-sprite.png
C11JiaochengCYuyanBianchengWangFix1/img/annotator-icon-sprite.png
C11JiaochengCYuyanBianchengWangFix1/img/apple-touch-icon.png
C11JiaochengCYuyanBianchengWangFix1/img/cancelfullscreen.png
C11JiaochengCYuyanBianchengWangFix1/img/close.png
C11JiaochengCYuyanBianchengWangFix1/img/fullscreen.png
C11JiaochengCYuyanBianchengWangFix1/img/loader.gif
C11JiaochengCYuyanBianchengWangFix1/img/menu-icon.png
C11JiaochengCYuyanBianchengWangFix1/img/save.png
C11JiaochengCYuyanBianchengWangFix1/img/saved.png
C11JiaochengCYuyanBianchengWangFix1/img/settings-s.png
C11JiaochengCYuyanBianchengWangFix1/img/settings.png
C11JiaochengCYuyanBianchengWangFix1/img/star.png
C11JiaochengCYuyanBianchengWangFix1/js/__init__.py
C11JiaochengCYuyanBianchengWangFix1/js/epub.js
C11JiaochengCYuyanBianchengWangFix1/js/epub.min.js
C11JiaochengCYuyanBianchengWangFix1/js/epub.min.map
C11JiaochengCYuyanBianchengWangFix1/js/hooks.min.js
C11JiaochengCYuyanBianchengWangFix1/js/hooks.min.map
C11JiaochengCYuyanBianchengWangFix1/js/reader.js
C11JiaochengCYuyanBianchengWangFix1/js/reader.js.map
C11JiaochengCYuyanBianchengWangFix1/js/reader.min.js
c_11_jiaocheng_c_yuyan_biancheng_wang_fix1-2025.3.24.0.dist-info/METADATA
c_11_jiaocheng_c_yuyan_biancheng_wang_fix1-2025.3.24.0.dist-info/WHEEL
c_11_jiaocheng_c_yuyan_biancheng_wang_fix1-2025.3.24.0.dist-info/entry_points.txt
c_11_jiaocheng_c_yuyan_biancheng_wang_fix1-2025.3.24.0.dist-info/top_level.txt
c_11_jiaocheng_c_yuyan_biancheng_wang_fix1-2025.3.24.0.dist-info/RECORD
